openapi_ext_tools-0.5.1-py3.9-nspkg.pth
openapi/spec/ext/__init__.py
openapi/spec/ext/cli/__init__.py
openapi/spec/ext/cli/main.py
openapi/spec/ext/spec/__init__.py
openapi/spec/ext/spec/base.py
openapi/spec/ext/utils/__init__.py
openapi/spec/ext/utils/log.py
openapi/spec/ext/utils/yaml.py
openapi_ext_tools-0.5.1.dist-info/LICENSE
openapi_ext_tools-0.5.1.dist-info/METADATA
openapi_ext_tools-0.5.1.dist-info/WHEEL
openapi_ext_tools-0.5.1.dist-info/entry_points.txt
openapi_ext_tools-0.5.1.dist-info/namespace_packages.txt
openapi_ext_tools-0.5.1.dist-info/top_level.txt
openapi_ext_tools-0.5.1.dist-info/RECORD
