Metadata-Version: 2.1
Name: openapi-ext-tools
Version: 0.5.1
Summary: Extended tools for openapi spec
Home-page: https://github.com/t2y/openapi-ext-tools
Author: Tetsuya Morimoto
Author-email: tetsuya.morimoto@gmail.com
License: Apache License 2.0
Platform: any
Classifier: License :: OSI Approved :: Apache Software License
Classifier: Development Status :: 3 - Alpha
Classifier: Intended Audience :: Developers
Classifier: Operating System :: OS Independent
Classifier: Programming Language :: Python :: 3
Classifier: Programming Language :: Python :: 3.7
Classifier: Programming Language :: Python :: 3.8
Classifier: Programming Language :: Python :: 3.9
Classifier: Programming Language :: Python :: 3.10
Classifier: Programming Language :: Python :: 3.11
Classifier: Programming Language :: Python :: Implementation :: CPython
Classifier: Environment :: Console
Classifier: Topic :: Software Development :: Libraries
Classifier: Topic :: Utilities
Requires-Dist: PyYAML
Requires-Dist: openapi-spec-validator (>=0.5.1)
